hive/service/__init__.py
hive/service/__version__.py
hive/service/logging.py
hive/service/py.typed
hive/service/service.py
hive_service-0.2.4.dist-info/METADATA
hive_service-0.2.4.dist-info/WHEEL
hive_service-0.2.4.dist-info/top_level.txt
hive_service-0.2.4.dist-info/RECORD
