Metadata-Version: 2.4
Name: hive-service
Version: 0.2.4
Summary: Common code for Hive services
Author-email: Gary Benson <gary@gbenson.net>
License-Expression: MIT
Project-URL: Homepage, https://github.com/gbenson/hive/tree/main/libs/service
Project-URL: Source, https://github.com/gbenson/hive
Requires-Dist: cloudevents[pydantic]
Requires-Dist: hive-common>=0.2.0
Requires-Dist: hive-messaging>=0.16.1
Requires-Dist: python-json-logger
